Metadata-Version: 1.0
Name: jas-calculator
Version: 0.1
Summary: Simple calculator
Home-page: UNKNOWN
Author: UNKNOWN
Author-email: UNKNOWN
License: UNKNOWN
Platform: UNKNOWN
